AUTHORS.txt
LICENSE.txt
MANIFEST.in
README.md
setup.cfg
setup.py
pyneo4j/__init__.py
pyneo4j/utils.py
pyneo4j.egg-info/PKG-INFO
pyneo4j.egg-info/SOURCES.txt
pyneo4j.egg-info/dependency_links.txt
pyneo4j.egg-info/requires.txt
pyneo4j.egg-info/top_level.txt
pyneo4j/core/__init__.py
pyneo4j/core/connection.py
pyneo4j/core/graph.py
pyneo4j/cypher/__init__.py
pyneo4j/cypher/node.py
pyneo4j/cypher/queries.py
pyneo4j/cypher/queryset.py
pyneo4j/cypher/relationship.py
pyneo4j/v2/__init__.py
pyneo4j/v2/graph.py
pyneo4j/v3/__init__.py
pyneo4j/v3/graph.py
tests/__init__.py
tests/tests.py