Metadata-Version: 1.1
Name: pyneo4j
Version: 0.0.0
Summary: A Python client library for Neo4j
Home-page: https://pyneo4j.readthedocs.org/en/latest/
Author: Renan Palmeira
Author-email: renanpalmeira1@hotmail.com
License: GPL
Keywords: neo4j pyramid flask django neo4j graph graphdb graphdatabase database rest client driver
Platform: UNKNOWN
Classifier: Development Status :: 3 - Alpha
Classifier: Intended Audience :: Developers
Classifier: License :: OSI Approved :: GNU General Public License (GPL)
Classifier: Operating System :: OS Independent
Classifier: Programming Language :: Python
Classifier: Programming Language :: Python :: 2
Classifier: Programming Language :: Python :: 2.7
Classifier: Programming Language :: Python :: 3
Classifier: Programming Language :: Python :: 3.4
Classifier: Programming Language :: Python :: 3.5 
